ftntdissect/__init__.py
ftntdissect/ftntdissect.py
ftntdissect-1.1.dist-info/LICENSE
ftntdissect-1.1.dist-info/METADATA
ftntdissect-1.1.dist-info/WHEEL
ftntdissect-1.1.dist-info/top_level.txt
ftntdissect-1.1.dist-info/RECORD
