Metadata-Version: 2.1
Name: ftntdissect
Version: 1.1
Summary: Package ftntdissect
Home-page: https://github.com/cgustave/ftntdissect
Author: Cedric GUSTAVE
Author-email: cgustave@free.fr
License: UNKNOWN
Platform: UNKNOWN
Classifier: Development Status :: 4 - Beta
Classifier: Programming Language :: Python :: 3
Classifier: License :: OSI Approved :: MIT License
Classifier: Operating System :: POSIX :: Linux
Classifier: Natural Language :: English
Classifier: Topic :: System :: Networking
Requires-Python: >=3.5
